latexcodec/__init__.py
latexcodec/codec.py
latexcodec/lexer.py
latexcodec-2.0.0.dist-info/AUTHORS.rst
latexcodec-2.0.0.dist-info/LICENSE.rst
latexcodec-2.0.0.dist-info/METADATA
latexcodec-2.0.0.dist-info/WHEEL
latexcodec-2.0.0.dist-info/top_level.txt
latexcodec-2.0.0.dist-info/zip-safe
latexcodec-2.0.0.dist-info/RECORD
