Metadata-Version: 1.1
Name: latexcodec
Version: 2.0.0
Summary: A lexer and codec to work with LaTeX code in Python.
Home-page: https://github.com/mcmtroffaes/latexcodec
Author: Matthias C. M. Troffaes
Author-email: matthias.troffaes@gmail.com
License: MIT
Download-URL: http://pypi.python.org/pypi/latexcodec
Platform: any
Classifier: Development Status :: 5 - Production/Stable
Classifier: Environment :: Console
Classifier: Intended Audience :: Developers
Classifier: License :: OSI Approved :: MIT License
Classifier: Operating System :: OS Independent
Classifier: Programming Language :: Python
Classifier: Programming Language :: Python :: 2
Classifier: Programming Language :: Python :: 2.7
Classifier: Programming Language :: Python :: 3
Classifier: Programming Language :: Python :: 3.3
Classifier: Programming Language :: Python :: 3.4
Classifier: Programming Language :: Python :: 3.5
Classifier: Programming Language :: Python :: 3.6
Classifier: Programming Language :: Python :: 3.7
Classifier: Topic :: Text Processing :: Markup :: LaTeX
Classifier: Topic :: Text Processing :: Filters
